odoo/addons/website_sale_free_qty/README.rst
odoo/addons/website_sale_free_qty/__init__.py
odoo/addons/website_sale_free_qty/__manifest__.py
odoo/addons/website_sale_free_qty/controllers/__init__.py
odoo/addons/website_sale_free_qty/controllers/main.py
odoo/addons/website_sale_free_qty/i18n/es.po
odoo/addons/website_sale_free_qty/i18n/website_sale_free_qty.pot
odoo/addons/website_sale_free_qty/models/__init__.py
odoo/addons/website_sale_free_qty/models/product_product.py
odoo/addons/website_sale_free_qty/models/product_template.py
odoo/addons/website_sale_free_qty/models/sale_order.py
odoo/addons/website_sale_free_qty/readme/CONFIGURE.rst
odoo/addons/website_sale_free_qty/readme/CONTRIBUTORS.rst
odoo/addons/website_sale_free_qty/readme/DESCRIPTION.rst
odoo/addons/website_sale_free_qty/readme/USAGE.rst
odoo/addons/website_sale_free_qty/static/description/availability_message.png
odoo/addons/website_sale_free_qty/static/description/icon.png
odoo/addons/website_sale_free_qty/static/description/index.html
odoo/addons/website_sale_free_qty/static/description/product_quantities.png
odoo/addons/website_sale_free_qty/tests/__init__.py
odoo/addons/website_sale_free_qty/tests/test_website_sale_stock_available.py
odoo13_addon_website_sale_free_qty-13.0.1.0.4.dev3.dist-info/METADATA
odoo13_addon_website_sale_free_qty-13.0.1.0.4.dev3.dist-info/WHEEL
odoo13_addon_website_sale_free_qty-13.0.1.0.4.dev3.dist-info/top_level.txt
odoo13_addon_website_sale_free_qty-13.0.1.0.4.dev3.dist-info/RECORD
